{"lastUsed":1647658325782,"path":"C:\/Users\/lidin\/javaavancado","projectCount":1,"recentFiles":[{"path":"\/agencia\/src\/main\/java\/com\/site\/agencia\/controllers","parentWorkspace":"C:\/Users\/lidin\/javaavancado","name":"DestinoController.java","lastModified":1647646188271,"locationURI":"file:\/C:\/Users\/lidin\/Downloads\/agencia\/src\/main\/java\/com\/site\/agencia\/controllers\/DestinoController.java"},{"path":"\/agencia\/src\/main\/java\/com\/site\/agencia\/repositorys","parentWorkspace":"C:\/Users\/lidin\/javaavancado","name":"ClienteRepository.java","lastModified":1647312933129,"locationURI":"file:\/C:\/Users\/lidin\/Downloads\/agencia\/src\/main\/java\/com\/site\/agencia\/repositorys\/ClienteRepository.java"},{"path":"\/agencia\/src\/main\/java\/com\/site\/agencia\/repositorys","parentWorkspace":"C:\/Users\/lidin\/javaavancado","name":"AgenciaRepository.java","lastModified":1647370770738,"locationURI":"file:\/C:\/Users\/lidin\/Downloads\/agencia\/src\/main\/java\/com\/site\/agencia\/repositorys\/AgenciaRepository.java"},{"path":"\/agencia","parentWorkspace":"C:\/Users\/lidin\/javaavancado","name":"pom.xml","lastModified":1647528088975,"locationURI":"file:\/C:\/Users\/lidin\/Downloads\/agencia\/pom.xml"},{"path":"\/agencia\/src\/main\/java\/com\/site\/agencia\/entities","parentWorkspace":"C:\/Users\/lidin\/javaavancado","name":"Agencia.java","lastModified":1647370236407,"locationURI":"file:\/C:\/Users\/lidin\/Downloads\/agencia\/src\/main\/java\/com\/site\/agencia\/entities\/Agencia.java"},{"path":"\/agencia\/src\/main\/java\/com\/site\/agencia\/repositorys","parentWorkspace":"C:\/Users\/lidin\/javaavancado","name":"DestinoRepository.java","lastModified":1647370616534,"locationURI":"file:\/C:\/Users\/lidin\/Downloads\/agencia\/src\/main\/java\/com\/site\/agencia\/repositorys\/DestinoRepository.java"},{"path":"\/agencia\/src\/main\/java\/com\/site\/agencia","parentWorkspace":"C:\/Users\/lidin\/javaavancado","name":"AgenciaApplication.java","lastModified":1647464198616,"locationURI":"file:\/C:\/Users\/lidin\/Downloads\/agencia\/src\/main\/java\/com\/site\/agencia\/AgenciaApplication.java"},{"path":"\/agencia\/src\/main\/resources","parentWorkspace":"C:\/Users\/lidin\/javaavancado","name":"application.properties","lastModified":1647527530607,"locationURI":"file:\/C:\/Users\/lidin\/Downloads\/agencia\/src\/main\/resources\/application.properties"},{"path":"\/agencia\/src\/main\/java\/com\/site\/agencia\/controllers","parentWorkspace":"C:\/Users\/lidin\/javaavancado","name":"ClienteController.java","lastModified":1647646188386,"locationURI":"file:\/C:\/Users\/lidin\/Downloads\/agencia\/src\/main\/java\/com\/site\/agencia\/controllers\/ClienteController.java"},{"path":"\/agencia\/src\/main\/java\/com\/site\/agencia\/entities","parentWorkspace":"C:\/Users\/lidin\/javaavancado","name":"Destino.java","lastModified":1647370236843,"locationURI":"file:\/C:\/Users\/lidin\/Downloads\/agencia\/src\/main\/java\/com\/site\/agencia\/entities\/Destino.java"},{"path":"\/agencia\/src\/main\/java\/com\/site\/agencia\/controllers","parentWorkspace":"C:\/Users\/lidin\/javaavancado","name":"AgenciaController.java","lastModified":1647646188472,"locationURI":"file:\/C:\/Users\/lidin\/Downloads\/agencia\/src\/main\/java\/com\/site\/agencia\/controllers\/AgenciaController.java"},{"path":"\/agencia\/src\/main\/java\/com\/site\/agencia\/entities","parentWorkspace":"C:\/Users\/lidin\/javaavancado","name":"Cliente.java","lastModified":1647370237155,"locationURI":"file:\/C:\/Users\/lidin\/Downloads\/agencia\/src\/main\/java\/com\/site\/agencia\/entities\/Cliente.java"}]}